qiling/__init__.py
qiling/const.py
qiling/core.py
qiling/core_hooks.py
qiling/core_hooks_types.py
qiling/core_struct.py
qiling/exception.py
qiling/host.py
qiling/log.py
qiling/utils.py
qiling/arch/__init__.py
qiling/arch/arch.py
qiling/arch/arm.py
qiling/arch/arm64.py
qiling/arch/arm64_const.py
qiling/arch/arm_const.py
qiling/arch/arm_utils.py
qiling/arch/cortex_m.py
qiling/arch/cortex_m_const.py
qiling/arch/mips.py
qiling/arch/mips_const.py
qiling/arch/msr.py
qiling/arch/ppc.py
qiling/arch/ppc_const.py
qiling/arch/register.py
qiling/arch/riscv.py
qiling/arch/riscv64.py
qiling/arch/riscv_const.py
qiling/arch/utils.py
qiling/arch/x86.py
qiling/arch/x86_const.py
qiling/arch/x86_utils.py
qiling/arch/evm/__init__.py
qiling/arch/evm/abc.py
qiling/arch/evm/abi.py
qiling/arch/evm/constants.py
qiling/arch/evm/evm.py
qiling/arch/evm/exceptions.py
qiling/arch/evm/hooks.py
qiling/arch/evm/typing.py
qiling/arch/evm/validation.py
qiling/arch/evm/_utils/__init__.py
qiling/arch/evm/_utils/address.py
qiling/arch/evm/_utils/bn128.py
qiling/arch/evm/_utils/datatypes.py
qiling/arch/evm/_utils/generator.py
qiling/arch/evm/_utils/numeric.py
qiling/arch/evm/_utils/padding.py
qiling/arch/evm/_utils/transactions.py
qiling/arch/evm/_utils/blake2/__init__.py
qiling/arch/evm/_utils/blake2/coders.py
qiling/arch/evm/_utils/blake2/compression.py
qiling/arch/evm/analysis/__init__.py
qiling/arch/evm/analysis/signatures.json
qiling/arch/evm/analysis/signatures.py
qiling/arch/evm/db/__init__.py
qiling/arch/evm/db/accesslog.py
qiling/arch/evm/db/account.py
qiling/arch/evm/db/atomic.py
qiling/arch/evm/db/batch.py
qiling/arch/evm/db/cache.py
qiling/arch/evm/db/diff.py
qiling/arch/evm/db/hash_trie.py
qiling/arch/evm/db/journal.py
qiling/arch/evm/db/keymap.py
qiling/arch/evm/db/slow_journal.py
qiling/arch/evm/db/storage.py
qiling/arch/evm/db/witness.py
qiling/arch/evm/db/backends/__init__.py
qiling/arch/evm/db/backends/base.py
qiling/arch/evm/db/backends/memory.py
qiling/arch/evm/precompiles/__init__.py
qiling-1.4.6.dist-info/COPYING
qiling-1.4.6.dist-info/METADATA
qiling-1.4.6.dist-info/WHEEL
qiling-1.4.6.dist-info/top_level.txt
qiling-1.4.6.dist-info/RECORD
