Metadata-Version: 2.1
Name: qiling
Version: 1.4.6
Summary: Qiling is an advanced binary emulation framework that cross-platform-architecture
Home-page: http://qiling.io
Maintainer: KaiJern Lau (xwings)
Maintainer-email: info@qiling.io
License: GPLv2
Keywords: qiling binary emulator framework malware analysis UEFI IoT
Classifier: Development Status :: 5 - Production/Stable
Classifier: Intended Audience :: Developers
Classifier: Topic :: Software Development :: Build Tools
Classifier: License :: OSI Approved :: GNU General Public License v2 (GPLv2)
Classifier: Programming Language :: Python :: 3
License-File: COPYING
Requires-Dist: capstone (>=4.0.1)
Requires-Dist: unicorn (>=2.0.1)
Requires-Dist: pefile (>=2022.5.30)
Requires-Dist: python-registry (>=1.3.1)
Requires-Dist: keystone-engine (>=0.9.2)
Requires-Dist: pyelftools (>=0.28)
Requires-Dist: gevent (>=20.9.0)
Requires-Dist: multiprocess (>=0.70.12.2)
Requires-Dist: pyyaml (>=6.0)
Requires-Dist: python-fx
Requires-Dist: questionary
Requires-Dist: termcolor
Requires-Dist: windows-curses (>=2.1.0) ; platform_system == "Windows"
Provides-Extra: re
Requires-Dist: r2libr (>=5.7.4) ; extra == 're'
Provides-Extra: evm
Requires-Dist: blake2b-py (>=0.1.2) ; extra == 'evm'
Requires-Dist: eth-keys (>=0.2.1) ; extra == 'evm'
Requires-Dist: eth-typing (>=2.2.0) ; extra == 'evm'
Requires-Dist: eth-utils (>=1.9.4) ; extra == 'evm'
Requires-Dist: eth-abi (>=2.1.1) ; extra == 'evm'
Requires-Dist: lru-dict (>=1.1.6) ; extra == 'evm'
Requires-Dist: py-ecc (>=1.4.7) ; extra == 'evm'
Requires-Dist: rlp (>=2) ; extra == 'evm'
Requires-Dist: trie (==2.0.0-alpha.5) ; extra == 'evm'
Requires-Dist: eth-hash[pycryptodome] ; extra == 'evm'
Requires-Dist: numpy ; extra == 'evm'
Requires-Dist: rich ; extra == 'evm'
Requires-Dist: cmd2 ; extra == 'evm'
Requires-Dist: cached-property (>=1.5.2) ; (python_version < "3.8") and extra == 'evm'
Requires-Dist: typing-extensions (>=3.7.4.3) ; (python_version < "3.8") and extra == 'evm'
Provides-Extra: fuzz
Requires-Dist: unicornafl (>=2.0.0) ; (platform_system != "Windows") and extra == 'fuzz'
Requires-Dist: fuzzercorn (>=0.0.1) ; (platform_system == "Linux") and extra == 'fuzz'
